SFRcalculator/__init__.py
SFRcalculator/sfr_calculator.py
SFRcalculator-0.1.1.dist-info/LICENSE
SFRcalculator-0.1.1.dist-info/METADATA
SFRcalculator-0.1.1.dist-info/WHEEL
SFRcalculator-0.1.1.dist-info/top_level.txt
SFRcalculator-0.1.1.dist-info/RECORD
