Metadata-Version: 2.1
Name: SFRcalculator
Version: 0.1.1
License-File: LICENSE
Requires-Dist: numpy
Requires-Dist: scikit-learn
Requires-Dist: pandas
Requires-Dist: matplotlib
